maxsim_fast-0.1.1.dist-info/METADATA
maxsim_fast-0.1.1.dist-info/WHEEL
maxsim_fast-0.1.1.dist-info/licenses/LICENSE
maxsim_fast/__init__.py
maxsim_fast/maxsim_fast.cpython-39-darwin.so
maxsim_fast-0.1.1.dist-info/RECORD
