Metadata-Version: 2.4
Name: maxsim-fast
Version: 0.1.1
Classifier: License :: OSI Approved :: Apache Software License
Classifier: Programming Language :: Python :: 3
Classifier: Programming Language :: Python :: 3.10
Classifier: Programming Language :: Python :: 3.11
Classifier: Programming Language :: Python :: 3.12
Classifier: Programming Language :: Python :: 3.13
Classifier: Programming Language :: Rust
Classifier: Operating System :: MacOS :: MacOS X
Classifier: Operating System :: Microsoft :: Windows
Classifier: Operating System :: POSIX :: Linux
Classifier: Topic :: Scientific/Engineering :: Artificial Intelligence
Requires-Dist: numpy>=1.20
License-File: LICENSE
Summary: Fast CPU implementation of MaxSim scoring
Keywords: maxsim,similarity,ranking,cpu,simd,performance
Author: Benjamin Clavié, Mixedbread Team
License: Apache-2.0
Requires-Python: >=3.8
Project-URL: Homepage, https://github.com/zhuwenxing/maxsim-cpu
Project-URL: Bug Tracker, https://github.com/zhuwenxing/maxsim-cpu/issues
